bigtiff_lzw_decompress.cpython-36m-darwin.so
bigtiff_lzw_decompress-0.0.0.dist-info/LICENSE
bigtiff_lzw_decompress-0.0.0.dist-info/METADATA
bigtiff_lzw_decompress-0.0.0.dist-info/WHEEL
bigtiff_lzw_decompress-0.0.0.dist-info/top_level.txt
bigtiff_lzw_decompress-0.0.0.dist-info/RECORD
