Metadata-Version: 2.1
Name: bigtiff-lzw-decompress
Version: 0.0.0
Summary: UNKNOWN
Home-page: UNKNOWN
Author: UNKNOWN
Author-email: UNKNOWN
License: UNKNOWN
Platform: UNKNOWN
Requires-Dist: Cython
